litellm2/.DS_Store
litellm2/__init__.py
litellm2/__pycache__/__init__.cpython-313.pyc
litellm2/agents/__init__.py
litellm2/agents/simple_agent.py
litellm2/agents/__pycache__/__init__.cpython-313.pyc
litellm2/agents/__pycache__/simple_agent.cpython-313.pyc
litellm2/client/__init__.py
litellm2/client/litellm_client.py
litellm2/client/message_handler.py
litellm2/client/__pycache__/__init__.cpython-313.pyc
litellm2/client/__pycache__/litellm_client.cpython-313.pyc
litellm2/client/__pycache__/message_handler.cpython-313.pyc
litellm2/config/__init__.py
litellm2/config/config.py
litellm2/config/__pycache__/__init__.cpython-313.pyc
litellm2/config/__pycache__/config.cpython-313.pyc
litellm2/models/__init__.py
litellm2/models/base_models.py
litellm2/models/__pycache__/__init__.cpython-312.pyc
litellm2/models/__pycache__/__init__.cpython-313.pyc
litellm2/models/__pycache__/__init__.cpython-39.pyc
litellm2/models/__pycache__/base_models.cpython-312.pyc
litellm2/models/__pycache__/base_models.cpython-313.pyc
litellm2/models/__pycache__/base_models.cpython-39.pyc
litellm2/utils/logger.py
litellm2/utils/__pycache__/logger.cpython-313.pyc
litellm2-1.0.6.dist-info/LICENSE
litellm2-1.0.6.dist-info/METADATA
litellm2-1.0.6.dist-info/WHEEL
litellm2-1.0.6.dist-info/top_level.txt
litellm2-1.0.6.dist-info/RECORD
