Metadata-Version: 2.2
Name: litellm2
Version: 1.0.6
Summary: A powerful AI framework with structured Pydantic responses, flexible LLM integration, and advanced agent capabilities
Home-page: https://github.com/markolofsen/litellm2
Author: Unrealos
Author-email: info@unrealos.com
License: MIT
Project-URL: Source, https://github.com/markolofsen/litellm2
Project-URL: Tracker, https://github.com/markolofsen/litellm2/issues
Project-URL: Documentation, https://github.com/markolofsen/litellm2#readme
Project-URL: Homepage, https://unrealos.com/
Classifier: Development Status :: 4 - Beta
Classifier: Intended Audience :: Developers
Classifier: Intended Audience :: Information Technology
Classifier: Intended Audience :: Science/Research
Classifier: Topic :: Software Development :: Libraries
Classifier: Topic :: Scientific/Engineering :: Artificial Intelligence
Classifier: Topic :: Text Processing :: Linguistic
Classifier: Programming Language :: Python :: 3.7
Classifier: Programming Language :: Python :: 3.8
Classifier: Programming Language :: Python :: 3.9
Classifier: Programming Language :: Python :: 3.10
Classifier: Programming Language :: Python :: 3.11
Classifier: License :: OSI Approved :: MIT License
Classifier: Operating System :: OS Independent
Requires-Python: >=3.7
License-File: LICENSE
Requires-Dist: litellm
Requires-Dist: pydantic
Requires-Dist: diskcache
Requires-Dist: smolagents
Requires-Dist: colorlog
Requires-Dist: drf-pydantic
Requires-Dist: typing-extensions
Requires-Dist: pyyaml
Provides-Extra: ui
Requires-Dist: smolagents[gradio]; extra == "ui"
Provides-Extra: dev
Requires-Dist: pytest; extra == "dev"
Requires-Dist: pytest-cov; extra == "dev"
Requires-Dist: black; extra == "dev"
Requires-Dist: flake8; extra == "dev"
Requires-Dist: isort; extra == "dev"
Requires-Dist: build; extra == "dev"
Requires-Dist: twine; extra == "dev"
Provides-Extra: all
Requires-Dist: smolagents[gradio]; extra == "all"
Requires-Dist: pytest; extra == "all"
Requires-Dist: pytest-cov; extra == "all"
Requires-Dist: black; extra == "all"
Requires-Dist: flake8; extra == "all"
Requires-Dist: isort; extra == "all"
Requires-Dist: build; extra == "all"
Requires-Dist: twine; extra == "all"
